petab_select/__init__.py
petab_select/candidate_space.py
petab_select/cli.py
petab_select/constants.py
petab_select/criteria.py
petab_select/descriptors.py
petab_select/handlers.py
petab_select/misc.py
petab_select/model.py
petab_select/model_space.py
petab_select/model_subspace.py
petab_select/petab.py
petab_select/problem.py
petab_select/ui.py
petab_select/validators.py
petab_select/version.py
petab_select-0.1.12.dist-info/LICENSE
petab_select-0.1.12.dist-info/METADATA
petab_select-0.1.12.dist-info/WHEEL
petab_select-0.1.12.dist-info/entry_points.txt
petab_select-0.1.12.dist-info/top_level.txt
petab_select-0.1.12.dist-info/RECORD
