Metadata-Version: 2.1
Name: petab_select
Version: 0.1.12
Summary: PEtab Select: an extension to PEtab for model selection.
Home-page: https://github.com/PEtab-dev/petab_select
Requires-Python: >=3.8
License-File: LICENSE
Requires-Dist: more-itertools
Requires-Dist: numpy
Requires-Dist: pandas
Requires-Dist: petab
Requires-Dist: pyyaml
Requires-Dist: click
Requires-Dist: dill
Provides-Extra: doc
Requires-Dist: sphinx <7,>=3.5.3 ; extra == 'doc'
Requires-Dist: sphinxcontrib-napoleon >=0.7 ; extra == 'doc'
Requires-Dist: sphinx-markdown-tables >=0.0.15 ; extra == 'doc'
Requires-Dist: sphinx-rtd-theme >=0.5.1 ; extra == 'doc'
Requires-Dist: recommonmark >=0.7.1 ; extra == 'doc'
Requires-Dist: nbsphinx ==0.9.1 ; extra == 'doc'
Requires-Dist: nbconvert <7.5.0 ; extra == 'doc'
Requires-Dist: ipython >=7.21.0 ; extra == 'doc'
Requires-Dist: readthedocs-sphinx-ext >=2.2.5 ; extra == 'doc'
Requires-Dist: sphinx-autodoc-typehints ; extra == 'doc'
Provides-Extra: test
Requires-Dist: pytest >=5.4.3 ; extra == 'test'
Requires-Dist: pytest-cov >=2.10.0 ; extra == 'test'
Requires-Dist: amici >=0.11.25 ; extra == 'test'
Requires-Dist: fides >=0.7.5 ; extra == 'test'
Requires-Dist: pypesto >0.2.13 ; extra == 'test'
